ipaclient/__init__.py
ipaclient/__main__.py
ipaclient/discovery.py
ipaclient/frontend.py
ipaclient/plugins/__init__.py
ipaclient/plugins/automember.py
ipaclient/plugins/automount.py
ipaclient/plugins/baseuser.py
ipaclient/plugins/ca.py
ipaclient/plugins/cert.py
ipaclient/plugins/certmap.py
ipaclient/plugins/certprofile.py
ipaclient/plugins/dns.py
ipaclient/plugins/hbacrule.py
ipaclient/plugins/hbactest.py
ipaclient/plugins/host.py
ipaclient/plugins/idrange.py
ipaclient/plugins/internal.py
ipaclient/plugins/location.py
ipaclient/plugins/migration.py
ipaclient/plugins/misc.py
ipaclient/plugins/otptoken.py
ipaclient/plugins/otptoken_yubikey.py
ipaclient/plugins/passwd.py
ipaclient/plugins/permission.py
ipaclient/plugins/rpcclient.py
ipaclient/plugins/server.py
ipaclient/plugins/service.py
ipaclient/plugins/stageuser.py
ipaclient/plugins/sudorule.py
ipaclient/plugins/topology.py
ipaclient/plugins/trust.py
ipaclient/plugins/user.py
ipaclient/plugins/vault.py
ipaclient/remote_plugins/__init__.py
ipaclient/remote_plugins/compat.py
ipaclient/remote_plugins/schema.py
ipaclient/remote_plugins/2_114/__init__.py
ipaclient/remote_plugins/2_114/aci.py
ipaclient/remote_plugins/2_114/automember.py
ipaclient/remote_plugins/2_114/automount.py
ipaclient/remote_plugins/2_114/batch.py
ipaclient/remote_plugins/2_114/cert.py
ipaclient/remote_plugins/2_114/config.py
ipaclient/remote_plugins/2_114/delegation.py
ipaclient/remote_plugins/2_114/dns.py
ipaclient/remote_plugins/2_114/group.py
ipaclient/remote_plugins/2_114/hbacrule.py
ipaclient/remote_plugins/2_114/hbacsvc.py
ipaclient/remote_plugins/2_114/hbacsvcgroup.py
ipaclient/remote_plugins/2_114/hbactest.py
ipaclient/remote_plugins/2_114/host.py
ipaclient/remote_plugins/2_114/hostgroup.py
ipaclient/remote_plugins/2_114/idrange.py
ipaclient/remote_plugins/2_114/idviews.py
ipaclient/remote_plugins/2_114/internal.py
ipaclient/remote_plugins/2_114/join.py
ipaclient/remote_plugins/2_114/krbtpolicy.py
ipaclient-4.12.2.dist-info/COPYING
ipaclient-4.12.2.dist-info/METADATA
ipaclient-4.12.2.dist-info/WHEEL
ipaclient-4.12.2.dist-info/entry_points.txt
ipaclient-4.12.2.dist-info/top_level.txt
ipaclient-4.12.2.dist-info/RECORD
